react/__init__.py
react/transforms/__init__.py
react/transforms/assign_sparse_to_dense.py
react/transforms/attach_index_notation.py
react/transforms/attach_iter_space_info.py
react/transforms/check_for_undefined.py
react/transforms/convert_matmul_op_to_call.py
react/transforms/convert_sparse_multiply_call.py
react/transforms/elide_convert_to_dense.py
react/transforms/fix_sparse_operand_to_left.py
react/transforms/gen_numba_code.py
react/transforms/insert_allocations.py
react/transforms/intraloop_scalar_replacement.py
react/transforms/mark_sparse_output.py
react/transforms/mark_transpose_ops.py
react/transforms/op_to_loop.py
react/transforms/parallelize.py
react/transforms/remove_none_axis.py
react/transforms/remove_unused_array_stores.py
react/transforms/sparsify_loops.py
react/transforms/to_inplace_sp_add_form.py
react/transforms/to_single_op_form.py
react/transforms/to_single_sparse_operand_form.py
react/transforms/trie_fuse.py
react/transforms/use_sparse_output.py
react/transforms/utils.py
react_compiler-0.1.15.dist-info/METADATA
react_compiler-0.1.15.dist-info/WHEEL
react_compiler-0.1.15.dist-info/top_level.txt
react_compiler-0.1.15.dist-info/RECORD
